README.md
setup.py
qgif/__init__.py
qgif/__main__.py
qgif/gen_lvgl_file.py
qgif/gif2png.py
qgif/qgif
qgif/qgif.py
qgif.egg-info/PKG-INFO
qgif.egg-info/SOURCES.txt
qgif.egg-info/dependency_links.txt
qgif.egg-info/requires.txt
qgif.egg-info/top_level.txt
qgif/qgif_C/libqgif.so