Metadata-Version: 2.1
Name: qgif
Version: 1.0.4
Summary: Convert GIF to QGIF, or decode QGIF.
Author: Hangzhou Nationalchip Inc.
Author-email: zhengdi@nationalchip.com
License: MIT Licence
Keywords: qgif nationalchip
Classifier: Development Status :: 3 - Alpha
Classifier: Intended Audience :: Developers
Classifier: Topic :: Software Development :: Libraries :: Python Modules
Classifier: License :: OSI Approved :: MIT License
Classifier: Programming Language :: Python :: 3
